datalayer/__init__.py
datalayer/__version__.py
datalayer/post-install.sh
datalayer-1.4.13.dist-info/METADATA
datalayer-1.4.13.dist-info/WHEEL
datalayer-1.4.13.dist-info/licenses/LICENSE
datalayer-1.4.13.dist-info/RECORD
