Metadata-Version: 2.1
Name: datalayer
Version: 1.4.13
Project-URL: Homepage, https://github.com/datalayer/datalayer
Project-URL: Documentation, https://docs.datalayer.tech
Project-URL: Repository, https://github.com/datalayer/datalayer
Project-URL: Issues, https://github.com/datalayer/datalayer/issues
Project-URL: Changelog, https://github.com/datalayer/datalayer/blob/main/CHANGELOG.md
License: 
License-File: LICENSE
Classifier: Framework :: Jupyter
Classifier: Framework :: Jupyter :: JupyterLab
Classifier: Framework :: Jupyter :: JupyterLab :: 4
Classifier: Framework :: Jupyter :: JupyterLab :: Extensions
Classifier: Framework :: Jupyter :: JupyterLab :: Extensions :: Prebuilt
Classifier: Intended Audience :: Developers
Classifier: Intended Audience :: Science/Research
Classifier: Intended Audience :: System Administrators
Classifier: License :: OSI Approved :: BSD License
Classifier: Programming Language :: Python
Classifier: Programming Language :: Python :: 3
Classifier: Programming Language :: Python :: 3.9
Classifier: Programming Language :: Python :: 3.10
Classifier: Programming Language :: Python :: 3.11
Requires-Python: >=3.9
Requires-Dist: datalayer-core==1.1.14
Requires-Dist: datalayer-ui==1.0.25
Requires-Dist: jupyter-iam==1.2.13
Requires-Dist: jupyter-kernels==1.2.21
Requires-Dist: jupyterlab<5,>=4.4.2
Provides-Extra: all
Requires-Dist: earthdata-mcp-server; extra == 'all'
Requires-Dist: jupyter-ai-agents; extra == 'all'
Requires-Dist: jupyter-collaboration; extra == 'all'
Requires-Dist: jupyter-contents; extra == 'all'
Requires-Dist: jupyter-docker; extra == 'all'
Requires-Dist: jupyter-kubernetes; extra == 'all'
Requires-Dist: jupyter-mcp-server; extra == 'all'
Provides-Extra: test
